observed.py
observed-0.5.3.dist-info/LICENSE.txt
observed-0.5.3.dist-info/METADATA
observed-0.5.3.dist-info/WHEEL
observed-0.5.3.dist-info/top_level.txt
observed-0.5.3.dist-info/RECORD
