Metadata-Version: 2.1
Name: observed
Version: 0.5.3
Summary: Observer pattern for functions and bound methods
Home-page: https://github.com/DanielSank/observed
Author: Daniel Sank
Author-email: sank.daniel@gmail.com
License: UNKNOWN
Platform: UNKNOWN
Classifier: Programming Language :: Python :: 3
Classifier: License :: OSI Approved :: MIT License
Classifier: Operating System :: OS Independent
